capnhook_ml.cpython-312-darwin.so
capnhook_ml-0.1.2.dist-info/RECORD
capnhook_ml-0.1.2.dist-info/WHEEL
capnhook_ml-0.1.2.dist-info/top_level.txt
capnhook_ml-0.1.2.dist-info/METADATA
capnhook_ml-0.1.2.dist-info/licenses/LICENSE
simd/reduce.hpp
simd/unary.hpp
simd/binary.hpp
simd/linalg.hpp
capnhook_ml.dylibs/libopenblas.0.3.dylib
