Metadata-Version: 2.4
Name: capnhook-ml
Version: 0.1.2
Summary: Optimised SIMD libary for machine learning
Author: ismaeelbashir03
Author-email: Ismaeel Bashir <ismaeelbashir2003@gmail.com>
License:                     GNU GENERAL PUBLIC LICENSE
Project-URL: Homepage, https://github.com/ismaeelbashir03/CapnHook-ML
Project-URL: Issue Tracker, https://github.com/ismaeelbashir03/CapnHook-ML/issues
Project-URL: Documentation, https://ismaeelbashir03.github.io/CapnHook-ML/
Classifier: Development Status :: 3 - Alpha
Classifier: Intended Audience :: Developers
Classifier: Topic :: Software Development :: Libraries
Classifier: License :: OSI Approved :: MIT License
Classifier: Programming Language :: Python :: 3.12
Classifier: Programming Language :: Python :: 3 :: Only
Classifier: Operating System :: OS Independent
Requires-Python: >=3.12
License-File: LICENSE
Requires-Dist: numpy>=2.2.5
Requires-Dist: conan>=1.65.0
Requires-Dist: nanobind
Dynamic: author
Dynamic: license-file
